flatfile_mapping-0.1.3.dist-info/METADATA
flatfile_mapping-0.1.3.dist-info/WHEEL
flatfile_mapping-0.1.3.dist-info/licenses/LICENSE
flatfile_mapping/__init__.py
flatfile_mapping/automapping.py
flatfile_mapping/filter.py
flatfile_mapping/mapping_program.py
flatfile_mapping/mapping_rule.py
flatfile_mapping/nesting.py
flatfile_mapping/py.typed
flatfile_mapping-0.1.3.dist-info/RECORD
