Metadata-Version: 2.1
Name: flatfile-mapping
Version: 0.1.3
Author-Email: Joel Grus <joel@flatfile.io>
License: MIT
Requires-Python: >=3.8
Requires-Dist: pydantic>=2.4.2
Requires-Dist: sympy>=1.12
Requires-Dist: lark>=1.1.8
Requires-Dist: requests>=2.31.0
Requires-Dist: pandas>=2.0.3; extra == "pandas"
Requires-Dist: pandas-stubs>=2.0.2.230605; extra == "pandas"
Provides-Extra: pandas
